README.md
setup.cfg
setup.py
grapher/core/__init__.py
grapher/core/constants.py
grapher/core/driver.py
grapher/core/errors.py
grapher/core/server.py
grapher_core.egg-info/PKG-INFO
grapher_core.egg-info/SOURCES.txt
grapher_core.egg-info/dependency_links.txt
grapher_core.egg-info/requires.txt
grapher_core.egg-info/top_level.txt