Metadata-Version: 1.2
Name: grapher-core
Version: 2.0.7
Summary: Grapher core server and libraries
Home-page: https://gitlab.com/grapher/grapher-core/
Author: Volodymyr Paslavskyy
Author-email: qfoxic@gmail.com
License: Apache Software License
Download-URL: https://gitlab.com/grapher/grapher-core/-/archive/2.0.7/grapher-core-2.0.7.tar.gz
Keywords: data,visualization,monitoring,graphs
Platform: UNKNOWN
Classifier: Development Status :: 5 - Production/Stable
Classifier: Intended Audience :: Developers
Classifier: Intended Audience :: System Administrators
Classifier: License :: OSI Approved :: Apache Software License
Classifier: Topic :: System :: Monitoring
Classifier: Topic :: System :: Systems Administration
Classifier: Programming Language :: Python :: 3.6
Classifier: Programming Language :: Python :: 3.7
Requires-Python: ~=3.7
